{"1": ["positive", "source", "test", "meeting", "pa", "surge", "covid", "loyalist", "gets", "lacks"]}
{"2": ["recount", "wisconsin", "certifies", "election", "fraud", "arizona", "confirms", "trump", "pennsylvania", "victory"]}
{"3": ["prescription", "canada", "exports", "drugs", "blocks", "bulk", "cindy", "drug", "world", "killing"]}
{"4": ["female", "communications", "ankle", "economic", "names", "twists", "press", "all", "receive", "briefing"]}
{"5": ["trump", "interview", "fox", "election", "maria", "lies", "ashamed", "earlier", "hours", "final"]}
{"6": ["protect", "swift", "advance", "quick", "lifting", "ban", "transgender", "moves", "plans", "exclude"]}
{"7": ["trump", "resigns", "scott", "atlas", "georgia", "needs", "official", "donald", "we", "adviser"]}
{"8": ["senate", "the", "georgia", "kelly", "lose", "black", "relief", "year", "you", "pennsylvania"]}
